aws_priv_actions/cli.py
aws_priv_actions-1.0.0.dist-info/METADATA
aws_priv_actions-1.0.0.dist-info/WHEEL
aws_priv_actions-1.0.0.dist-info/entry_points.txt
aws_priv_actions-1.0.0.dist-info/licenses/LICENSE
aws_priv_actions-1.0.0.dist-info/RECORD
