Metadata-Version: 2.4
Name: aws-priv-actions
Version: 1.0.0
Summary: CLI for privileged actions on AWS member accounts
Author-email: Matt Clarke <futurebird1@protonmail.com>
License-Expression: MIT
License-File: LICENSE
Requires-Python: >=3.10
Requires-Dist: boto3>=1.38.0
Requires-Dist: rich>=13.0.0
Requires-Dist: typer>=0.9.0
